text_file_to_pdf/__init__.py
text_file_to_pdf/main.py
text_file_to_pdf-0.0.11.dist-info/licenses/LICENSE
text_file_to_pdf-0.0.11.dist-info/METADATA
text_file_to_pdf-0.0.11.dist-info/WHEEL
text_file_to_pdf-0.0.11.dist-info/entry_points.txt
text_file_to_pdf-0.0.11.dist-info/top_level.txt
text_file_to_pdf-0.0.11.dist-info/RECORD
