Metadata-Version: 2.4
Name: text-file-to-pdf
Version: 0.0.11
Summary: A Python-based tool converting a text file to a PDF file
Author-email: Philip Moore <prmoore77@hotmail.com>, Stephen Weber <sweber@truckcab.com>
License-Expression: Apache-2.0
Project-URL: Homepage, https://github.com/TruckCab/text-file-to-pdf
Keywords: oracle,object,tracker,git,ddl
Classifier: Programming Language :: Python
Classifier: Programming Language :: Python :: 3
Requires-Python: >=3.10
License-File: LICENSE
Requires-Dist: click==8.2.*
Requires-Dist: codetiming==1.4.*
Requires-Dist: fpdf2==2.8.*
Provides-Extra: dev
Requires-Dist: bumpver; extra == "dev"
Requires-Dist: pip-tools; extra == "dev"
Requires-Dist: pytest; extra == "dev"
Dynamic: license-file
